legend_pygeom_optics-0.14.1.dist-info/licenses/LICENSE
legendoptics/__init__.py
legendoptics/_version.py
legendoptics/cli.py
legendoptics/copper.py
legendoptics/fibers.py
legendoptics/germanium.py
legendoptics/lar.py
legendoptics/nylon.py
legendoptics/pen.py
legendoptics/plot.py
legendoptics/pmts.py
legendoptics/pyg4utils.py
legendoptics/scintillate.py
legendoptics/silica.py
legendoptics/silicon.py
legendoptics/store.py
legendoptics/tetratex.py
legendoptics/tpb.py
legendoptics/tyvek.py
legendoptics/ultem.py
legendoptics/utils.py
legendoptics/vm2000.py
legendoptics/water.py
legendoptics/data/cu_reflectivity.dat
legendoptics/data/ge_reflectivity.dat
legendoptics/data/lar_emission_heindl2010.dat
legendoptics/data/nylon_absorption.dat
legendoptics/data/pen_abslength.dat
legendoptics/data/pen_wlscomponent.dat
legendoptics/data/pmt_etl9354kb_qe.dat
legendoptics/data/pmt_r7081_qe.dat
legendoptics/data/psfibers_wlsabslength.dat
legendoptics/data/psfibers_wlscomponent.dat
legendoptics/data/si_rindex_imag.dat
legendoptics/data/si_rindex_real.dat
legendoptics/data/tetratex_reflectivity.dat
legendoptics/data/tpb_polystyrene_wlscomponent.dat
legendoptics/data/tpb_wlsabslength.dat
legendoptics/data/tpb_wlsr_wlscomponent.dat
legendoptics/data/tyvek_reflectivity.dat
legendoptics/data/ultem_rindex.dat
legendoptics/data/ultem_rindex_imag.dat
legendoptics/data/vm2000_em_spec.dat
legend_pygeom_optics-0.14.1.dist-info/METADATA
legend_pygeom_optics-0.14.1.dist-info/WHEEL
legend_pygeom_optics-0.14.1.dist-info/entry_points.txt
legend_pygeom_optics-0.14.1.dist-info/top_level.txt
legend_pygeom_optics-0.14.1.dist-info/RECORD
