Metadata-Version: 2.4
Name: legend_pygeom_optics
Version: 0.14.1
Summary: Optical properties of the LEGEND experiment
Author-email: Luigi Pertoldi <gipert@pm.me>, Manuel Huber <info@manuelhu.de>
Maintainer: The LEGEND Collaboration
License:                     GNU GENERAL PUBLIC LICENSE
Project-URL: Homepage, https://github.com/legend-exp/legend-pygeom-optics
Project-URL: Bug Tracker, https://github.com/legend-exp/legend-pygeom-optics/issues
Project-URL: Discussions, https://github.com/legend-exp/legend-pygeom-optics/discussions
Project-URL: Changelog, https://github.com/legend-exp/legend-pygeom-optics/releases
Classifier: Intended Audience :: Developers
Classifier: Intended Audience :: Science/Research
Classifier: License :: OSI Approved :: GNU General Public License v3 (GPLv3)
Classifier: Operating System :: MacOS
Classifier: Operating System :: POSIX
Classifier: Operating System :: Unix
Classifier: Programming Language :: Python
Classifier: Programming Language :: Python :: 3
Classifier: Programming Language :: Python :: 3 :: Only
Classifier: Topic :: Scientific/Engineering
Requires-Python: >=3.10
License-File: LICENSE
Requires-Dist: importlib_resources
Requires-Dist: numba
Requires-Dist: numpy
Requires-Dist: matplotlib
Requires-Dist: pint>=0.24.1
Requires-Dist: pyg4ometry
Requires-Dist: scipy
Provides-Extra: all
Requires-Dist: legend-pygeom-optics[docs,test]; extra == "all"
Provides-Extra: docs
Requires-Dist: furo; extra == "docs"
Requires-Dist: myst-parser; extra == "docs"
Requires-Dist: sphinx; extra == "docs"
Requires-Dist: sphinx-copybutton; extra == "docs"
Provides-Extra: test
Requires-Dist: pre-commit; extra == "test"
Requires-Dist: pytest>=6.0; extra == "test"
Requires-Dist: pytest-cov; extra == "test"
Dynamic: license-file
